direct-stubs/__init__.pyi
direct-stubs/_typing.pyi
direct-stubs/actor/Actor.pyi
direct-stubs/actor/DistributedActor.pyi
direct-stubs/actor/__init__.pyi
direct-stubs/cluster/ClusterClient.pyi
direct-stubs/cluster/ClusterConfig.pyi
direct-stubs/cluster/ClusterMsgs.pyi
direct-stubs/cluster/ClusterServer.pyi
direct-stubs/cluster/__init__.pyi
direct-stubs/controls/BattleWalker.pyi
direct-stubs/controls/ControlManager.pyi
direct-stubs/controls/DevWalker.pyi
direct-stubs/controls/GhostWalker.pyi
direct-stubs/controls/GravityWalker.pyi
direct-stubs/controls/InputState.pyi
direct-stubs/controls/NonPhysicsWalker.pyi
direct-stubs/controls/ObserverWalker.pyi
direct-stubs/controls/PhysicsRoller.pyi
direct-stubs/controls/PhysicsWalker.pyi
direct-stubs/controls/SwimWalker.pyi
direct-stubs/controls/TwoDWalker.pyi
direct-stubs/controls/__init__.pyi
direct-stubs/directbase/DirectStart.pyi
direct-stubs/directbase/TestStart.pyi
direct-stubs/directbase/ThreeUpStart.pyi
direct-stubs/directbase/__init__.pyi
direct-stubs/directdevices/DirectDeviceManager.pyi
direct-stubs/directdevices/DirectFastrak.pyi
direct-stubs/directdevices/DirectJoybox.pyi
direct-stubs/directdevices/DirectRadamec.pyi
direct-stubs/directdevices/__init__.pyi
direct-stubs/directnotify/DirectNotify.pyi
direct-stubs/directnotify/DirectNotifyGlobal.pyi
direct-stubs/directnotify/Logger.pyi
direct-stubs/directnotify/LoggerGlobal.pyi
direct-stubs/directnotify/Notifier.pyi
direct-stubs/directnotify/RotatingLog.pyi
direct-stubs/directnotify/__init__.pyi
direct-stubs/directscripts/__init__.pyi
direct-stubs/directscripts/eggcacher.pyi
direct-stubs/directscripts/extract_docs.pyi
direct-stubs/directscripts/gendocs.pyi
direct-stubs/directtools/DirectCameraControl.pyi
direct-stubs/directtools/DirectGeometry.pyi
direct-stubs/directtools/DirectGlobals.pyi
direct-stubs/directtools/DirectGrid.pyi
direct-stubs/directtools/DirectLights.pyi
direct-stubs/directtools/DirectManipulation.pyi
direct-stubs/directtools/DirectSelection.pyi
types_panda3d-0.4.1.dist-info/LICENSE
types_panda3d-0.4.1.dist-info/METADATA
types_panda3d-0.4.1.dist-info/WHEEL
types_panda3d-0.4.1.dist-info/top_level.txt
types_panda3d-0.4.1.dist-info/RECORD
