Metadata-Version: 2.1
Name: types-panda3d
Version: 0.4.1
Summary: Type stubs for the Panda3D Python bindings
Author: W. M. Okiishi
License: Copyright (c) 2022 W. M. Okiishi
Project-URL: Homepage, https://github.com/WMOkiishi/types-panda3d
Project-URL: Bug Tracker, https://github.com/WMOkiishi/types-panda3d/issues
Classifier: Programming Language :: Python :: 3
Classifier: License :: OSI Approved :: MIT License
Classifier: Operating System :: OS Independent
Requires-Python: >=3.8
License-File: LICENSE
